{
  "arch": "x86_64",
  "build": "ha770c72_1",
  "build_number": 1,
  "channel": "https://conda.anaconda.org/conda-forge/noarch/",
  "constrains": [],
  "depends": [
    "libfabric1 2.1.0 hf45584d_1"
  ],
  "fn": "libfabric-2.1.0-ha770c72_1.conda",
  "license": "BSD-2-Clause OR GPL-2.0-only",
  "license_family": "BSD",
  "md5": "a3419b2895a32e0748a254be58efb7a8",
  "name": "libfabric",
  "platform": "linux",
  "sha256": "d07cdd0613bae31ec30410a419078cd8ba60be4727563f863cc39e7cd81620c8",
  "size": 14083,
  "subdir": "linux-64",
  "timestamp": 1745592773000,
  "url": "https://conda.anaconda.org/conda-forge/linux-64/libfabric-2.1.0-ha770c72_1.conda",
  "version": "2.1.0"
}